{
  "Program": "program_071", 
  "Functions": [
    {
      "Control Flow": {
        "Cyclomatic Complexity": 19, 
        "Edges": 68, 
        "Nodes": 51, 
        "Conditions": 19
      }, 
      "Structural Features": {
        "Instruction Count": 236, 
        "Basic Block Count": 51
      }, 
      "Function Boundaries": {
        "Entry Point": "0x00100000", 
        "Function Size": 921, 
        "Name": "strange_sort_list"
      }
    }, 
    {
      "Control Flow": {
        "Cyclomatic Complexity": 2, 
        "Edges": 0, 
        "Nodes": 0, 
        "Conditions": 0
      }, 
      "Structural Features": {
        "Instruction Count": 0, 
        "Basic Block Count": 0
      }, 
      "Function Boundaries": {
        "Entry Point": "0x00101000", 
        "Function Size": 1, 
        "Name": "operator.new"
      }
    }, 
    {
      "Control Flow": {
        "Cyclomatic Complexity": 2, 
        "Edges": 0, 
        "Nodes": 0, 
        "Conditions": 0
      }, 
      "Structural Features": {
        "Instruction Count": 0, 
        "Basic Block Count": 0
      }, 
      "Function Boundaries": {
        "Entry Point": "0x00101008", 
        "Function Size": 1, 
        "Name": "memcpy"
      }
    }, 
    {
      "Control Flow": {
        "Cyclomatic Complexity": 2, 
        "Edges": 0, 
        "Nodes": 0, 
        "Conditions": 0
      }, 
      "Structural Features": {
        "Instruction Count": 0, 
        "Basic Block Count": 0
      }, 
      "Function Boundaries": {
        "Entry Point": "0x00101010", 
        "Function Size": 1, 
        "Name": "operator.delete"
      }
    }, 
    {
      "Control Flow": {
        "Cyclomatic Complexity": 2, 
        "Edges": 0, 
        "Nodes": 0, 
        "Conditions": 0
      }, 
      "Structural Features": {
        "Instruction Count": 0, 
        "Basic Block Count": 0
      }, 
      "Function Boundaries": {
        "Entry Point": "0x00101020", 
        "Function Size": 1, 
        "Name": "_Unwind_Resume"
      }
    }, 
    {
      "Control Flow": {
        "Cyclomatic Complexity": 2, 
        "Edges": 0, 
        "Nodes": 0, 
        "Conditions": 0
      }, 
      "Structural Features": {
        "Instruction Count": 0, 
        "Basic Block Count": 0
      }, 
      "Function Boundaries": {
        "Entry Point": "0x00101028", 
        "Function Size": 1, 
        "Name": "memmove"
      }
    }
  ], 
  "Function Count": 6
}